sahomedb-0.4.0.dist-info/METADATA
sahomedb-0.4.0.dist-info/WHEEL
sahomedb/vector.pyi
sahomedb/prelude.pyi
sahomedb/collection.pyi
sahomedb/database.pyi
sahomedb/py.typed
sahomedb/__init__.py
sahomedb/sahomedb.cpython-310-x86_64-linux-gnu.so
sahomedb-0.4.0.dist-info/RECORD
