Metadata-Version: 2.3
Name: sahomedb
Version: 0.4.0
Classifier: Intended Audience :: Developers
Classifier: License :: OSI Approved :: Apache Software License
Classifier: Programming Language :: Rust
Classifier: Topic :: Database
Classifier: Topic :: Text Processing :: Indexing
Summary: Fast embedded vector database with incremental HNSW indexing.
Keywords: embedded,vector,database,hnsw,ann
Home-Page: https://sahome.com/
Author: Elijah Obs, Samson
License: Apache-2.0
Requires-Python: >=3.8
Project-URL: repository, https://github.com/Sahomey-Technologies/sahomedb
Project-URL: issues, https://github.com/Sahomey-Technologies/sahomedb/issues
Project-URL: changelog, https://github.com/Sahomey-Technologies/sahomedb/blob/main/docs/changelog.md
